naver_translation/__init__.py
naver_translation/error.py
naver_translation/model.py
naver_translation/naver.py
naver_translation/utils.py
naver_translation-2.1.0.dist-info/METADATA
naver_translation-2.1.0.dist-info/WHEEL
naver_translation-2.1.0.dist-info/top_level.txt
naver_translation-2.1.0.dist-info/RECORD
