Metadata-Version: 2.1
Name: naver-translation
Version: 2.1.0
Summary: 네이버 API를 사용한 비공식 번역 라이브러리입니다.
Home-page: https://github.com/VoidAsMad/Naver_Translation
Author: VoidAsMad
Author-email: voidasmad@gmail.com
License: MIT
Platform: UNKNOWN
Requires-Python: >=3
